x_whatsapp/__init__.py
x_whatsapp-0.1.2.dist-info/LICENSE
x_whatsapp-0.1.2.dist-info/WHEEL
x_whatsapp-0.1.2.dist-info/METADATA
x_whatsapp-0.1.2.dist-info/RECORD
