Metadata-Version: 2.1
Name: x-whatsapp
Version: 0.1.2
Summary: A Playwright-based WhatsApp client to interact with x-cortex.
Author-email: Prathwik Kushal Kumar <prathwiklog@gmail.com>, Kausthubh J Rao <kausthubhjrao@gmail.com>
Requires-Python: >=3.8
Classifier: Programming Language :: Python :: 3
Classifier: License :: OSI Approved :: MIT License
Classifier: Operating System :: OS Independent
Classifier: Topic :: Communications :: Chat
Requires-Dist: playwright>=1.33.0
Requires-Dist: asyncio>=3.4.3
Requires-Dist: typing-extensions>=4.5.0
Project-URL: Documentation, https://github.com/x-cortex/x-whatsapp#readme
Project-URL: Homepage, https://github.com/x-cortex/x-whatsapp
Project-URL: Repository, https://github.com/x-cortex/x-whatsapp
